ahui_aiohttp_server/__init__.py
ahui_aiohttp_server-0.1.16.dist-info/METADATA
ahui_aiohttp_server-0.1.16.dist-info/RECORD
ahui_aiohttp_server-0.1.16.dist-info/WHEEL
ahui_aiohttp_server-0.1.16.dist-info/top_level.txt
