Metadata-Version: 2.1
Name: ahui-aiohttp-server
Version: 0.1.16
Summary: Simple aiohttp Server for both static and python/php file
Home-page: http://github.com/ahuigo/ahui-aiohttp-server
Author: ahuigo
Author-email: nobody@qq.com
License: MIT
Platform: UNKNOWN
Classifier: License :: OSI Approved :: MIT License
Classifier: Natural Language :: English
Classifier: Operating System :: OS Independent
Classifier: Programming Language :: Python :: 3
Requires-Python: >=3.5.3
Requires-Dist: aiohttp
